CHANGES
LICENSE
MANIFEST.in
README
setup.cfg
setup.py
test_sqlalchemy.py
Flask_SQLAlchemy_tw.egg-info/PKG-INFO
Flask_SQLAlchemy_tw.egg-info/SOURCES.txt
Flask_SQLAlchemy_tw.egg-info/dependency_links.txt
Flask_SQLAlchemy_tw.egg-info/not-zip-safe
Flask_SQLAlchemy_tw.egg-info/requires.txt
Flask_SQLAlchemy_tw.egg-info/top_level.txt
docs/Makefile
docs/api.rst
docs/binds.rst
docs/changelog.rst
docs/conf.py
docs/config.rst
docs/contents.rst.inc
docs/contexts.rst
docs/flaskstyle.sty
docs/index.rst
docs/logo.pdf
docs/make.bat
docs/models.rst
docs/queries.rst
docs/quickstart.rst
docs/signals.rst
docs/_static/flask-sqlalchemy-small.png
docs/_static/flask-sqlalchemy.png
docs/_templates/sidebarintro.html
docs/_templates/sidebarlogo.html
flask_sqlalchemy/__init__.py
flask_sqlalchemy/_compat.py